utilitybetammar/__init__.py
utilitybetammar/constants.py
utilitybetammar/utitlitybetammar.py
utilitybetammar-0.0.1.dist-info/METADATA
utilitybetammar-0.0.1.dist-info/WHEEL
utilitybetammar-0.0.1.dist-info/top_level.txt
utilitybetammar-0.0.1.dist-info/RECORD
